ducolib.py
ducolib-0.0.4.dist-info/LICENSE.txt
ducolib-0.0.4.dist-info/METADATA
ducolib-0.0.4.dist-info/WHEEL
ducolib-0.0.4.dist-info/top_level.txt
ducolib-0.0.4.dist-info/RECORD
