Metadata-Version: 2.1
Name: ducolib
Version: 0.0.4
Summary: Duino-Coin Mining library for Python.
Home-page: https://github.com/Alicia426/ducolib
Author: Alicia426
Author-email: alicia426@protonmail.com
License: UNKNOWN
Platform: UNKNOWN
Classifier: Programming Language :: Python :: 3
Classifier: License :: OSI Approved :: MIT License
Classifier: Operating System :: OS Independent
Requires-Python: >=3.6
